{"data":[{"breadcrumb":[{"canonical":"/beautify","categories":[],"fullurl":"/beautify","idpath":"|2|","internalid":"2","isprimaryurl":true,"name":"Shop Beautify","parenturl":""}],"canonical":"/beautify","categories":[{"canonical":"/beautify/hair-extension-tapes","categories":[],"fullurl":"/beautify/hair-extension-tapes","idpath":"|2|11|","internalid":"11","isprimaryurl":true,"name":"Hair Extension Tapes","parenturl":"/beautify","sequencenumber":"0.0","thumbnailurl":"/core/media/media.nl?id=36369&c=8359882&h=SgQ-zP7MKuleDQC4P4S-FRbMguuljW_xmXc7HQTLuFeXVAwZ","urlfragment":"hair-extension-tapes"},{"canonical":"/beautify/adhesive-removers","categories":[],"fullurl":"/beautify/adhesive-removers","idpath":"|2|12|","internalid":"12","isprimaryurl":true,"name":"Adhesive Removers","parenturl":"/beautify","sequencenumber":"1.0","thumbnailurl":"/core/media/media.nl?id=36373&c=8359882&h=B6duBi78Mvlsb1qufdYvtn5OKI9yEIRLj-rmfgtYUOGc1oMo","urlfragment":"adhesive-removers"},{"canonical":"/beautify/preparation","categories":[],"fullurl":"/beautify/preparation","idpath":"|2|13|","internalid":"13","isprimaryurl":true,"name":"Preparation","parenturl":"/beautify","sequencenumber":"2.0","thumbnailurl":"/core/media/media.nl?id=36399&c=8359882&h=MD1KDZ7YFNhZ1YXWbRl4VcnU2ynU4q3Xnzl-Mjegv3u4B_EZ","urlfragment":"preparation"},{"canonical":"/beautify/system-care","categories":[],"fullurl":"/beautify/system-care","idpath":"|2|14|","internalid":"14","isprimaryurl":true,"name":"System Care","parenturl":"/beautify","sequencenumber":"3.0","thumbnailurl":"/core/media/media.nl?id=36400&c=8359882&h=4Y4UTd3Z6bAjIx7M2hmiRYKndjC0KyyMUMaA9wXD82ymhqLJ","urlfragment":"system-care"}],"_debug_requestTime":15,"fullurl":"/beautify","idpath":"|2|","internalid":"2","isprimaryurl":true,"metadescription":"Transform your look with Beautify! Our premium quality hair extension adhesives are designed to enhance your natural beauty and give you the luscious locks you've always dreamed of. Shop now and enjoy high-quality, long-lasting results with Walker Tape Co.","name":"Shop Beautify","pagetitle":"Beautify | Walker Tape","parenturl":"","urlfragment":"beautify"}]}